{
  "?xml": {
    "@version": "1.0",
    "@encoding": "UTF-8"
  },
  "kml": {
    "@xmlns": "http://www.opengis.net/kml/2.2",
    "@xmlns:gx": "http://www.google.com/kml/ext/2.2",
    "Document": {
      "name": " Location history from 2017-12-17 to 2017-12-17 ",
      "open": "1",
      "description": "",
      "StyleMap": {
        "@id": "multiTrack",
        "Pair": [
          {
            "key": "normal",
            "styleUrl": "#multiTrack_n"
          },
          {
            "key": "highlight",
            "styleUrl": "#multiTrack_h"
          }
        ]
      },
      "Style": [
        {
          "@id": "multiTrack_n",
          "IconStyle": {
            "Icon": {
              "href": "https://earth.google.com/images/kml-icons/track-directional/track-0.png"
            }
          },
          "LineStyle": {
            "color": "99ffac59",
            "width": "6"
          }
        },
        {
          "@id": "multiTrack_h",
          "IconStyle": {
            "scale": "1.2",
            "Icon": {
              "href": "https://earth.google.com/images/kml-icons/track-directional/track-0.png"
            }
          },
          "LineStyle": {
            "color": "99ffac59",
            "width": "8"
          }
        }
      ],
      "Placemark": [
        {
          "name": "Home",
          "address": "7 Jackes Ave, Toronto, ON M4T 1E3",
          "ExtendedData": {
            "Data": [
              {
                "@name": "Email",
                "value": "melikesolenakin@gmail.com"
              },
              {
                "@name": "Category",
                "value": ""
              },
              {
                "@name": "Distance",
                "value": "0"
              }
            ]
          },
          "description": "  from 2017-12-16T22:05:01.219Z to 2017-12-17T19:22:08.389Z. Distance 0m ",
          "Point": {
            "coordinates": ""
          },
          "gx:Track": {
            "altitudeMode": {
              "@xmlns": "http://www.opengis.net/kml/2.2",
              "#text": "clampToGround"
            },
            "gx:coord": "-79.3916563 43.6847358 0"
          },
          "TimeSpan": {
            "begin": "2017-12-16T22:05:01.219Z",
            "end": "2017-12-17T19:22:08.389Z"
          }
        },
        {
          "name": "On the subway",
          "address": "",
          "ExtendedData": {
            "Data": [
              {
                "@name": "Email",
                "value": "melikesolenakin@gmail.com"
              },
              {
                "@name": "Category",
                "value": "On the subway"
              },
              {
                "@name": "Distance",
                "value": "3614"
              }
            ]
          },
          "description": " On the subway from 2017-12-17T19:22:08.389Z to 2017-12-17T19:37:24.838Z. Distance 3614m ",
          "Point": {
            "coordinates": ""
          },
          "gx:Track": {
            "altitudeMode": {
              "@xmlns": "http://www.opengis.net/kml/2.2",
              "#text": "clampToGround"
            },
            "gx:coord": [
              "-79.3916563 43.6847358 0",
              "-79.3916563 43.6847358 0",
              "-79.3925548 43.683752 0",
              "-79.3908718 43.6821511 0",
              "-79.3885104 43.6767076 0",
              "-79.3807342 43.6546528 0",
              "-79.38062989714014 43.65380643017431 0",
              "-79.38062989714014 43.65380643017431 0"
            ]
          },
          "TimeSpan": {
            "begin": "2017-12-17T19:22:08.389Z",
            "end": "2017-12-17T19:37:24.838Z"
          }
        },
        {
          "name": "Downtown Yonge",
          "address": "Toronto, ON",
          "ExtendedData": {
            "Data": [
              {
                "@name": "Email",
                "value": "melikesolenakin@gmail.com"
              },
              {
                "@name": "Category",
                "value": ""
              },
              {
                "@name": "Distance",
                "value": "0"
              }
            ]
          },
          "description": "  from 2017-12-17T19:37:24.838Z to 2017-12-17T21:14:29.821Z. Distance 0m ",
          "Point": {
            "coordinates": ""
          },
          "gx:Track": {
            "altitudeMode": {
              "@xmlns": "http://www.opengis.net/kml/2.2",
              "#text": "clampToGround"
            },
            "gx:coord": "-79.3817523 43.6574254 0"
          },
          "TimeSpan": {
            "begin": "2017-12-17T19:37:24.838Z",
            "end": "2017-12-17T21:14:29.821Z"
          }
        },
        {
          "name": "Walking",
          "address": "",
          "ExtendedData": {
            "Data": [
              {
                "@name": "Email",
                "value": "melikesolenakin@gmail.com"
              },
              {
                "@name": "Category",
                "value": "Walking"
              },
              {
                "@name": "Distance",
                "value": "1505"
              }
            ]
          },
          "description": " Walking from 2017-12-17T21:14:29.821Z to 2017-12-17T21:49:17.607Z. Distance 1505m ",
          "Point": {
            "coordinates": ""
          },
          "gx:Track": {
            "altitudeMode": {
              "@xmlns": "http://www.opengis.net/kml/2.2",
              "#text": "clampToGround"
            },
            "gx:coord": [
              "-79.38062989714014 43.65380643017431 0",
              "-79.38062989714014 43.65380643017431 0",
              "-79.3805584 43.6532544 0",
              "-79.3808665 43.6545202 0",
              "-79.3807182 43.6555252 0",
              "-79.3835864 43.6555861 0",
              "-79.3859585 43.6551088 0",
              "-79.3836143 43.6561151 0",
              "-79.382722 43.6559413 0",
              "-79.3808929 43.6544825 0",
              "-79.3802339 43.6526458 0",
              "-79.38061499999999 43.652823 0",
              "-79.38061499999999 43.652823 0"
            ]
          },
          "TimeSpan": {
            "begin": "2017-12-17T21:14:29.821Z",
            "end": "2017-12-17T21:49:17.607Z"
          }
        },
        {
          "name": "Apple Eaton Centre",
          "address": "220 Yonge St, Toronto, ON M5B 2H1",
          "ExtendedData": {
            "Data": [
              {
                "@name": "Email",
                "value": "melikesolenakin@gmail.com"
              },
              {
                "@name": "Category",
                "value": "Electronics Store"
              },
              {
                "@name": "Distance",
                "value": "0"
              }
            ]
          },
          "description": " Electronics Store from 2017-12-17T21:49:17.607Z to 2017-12-17T22:58:04.389Z. Distance 0m ",
          "Point": {
            "coordinates": ""
          },
          "gx:Track": {
            "altitudeMode": {
              "@xmlns": "http://www.opengis.net/kml/2.2",
              "#text": "clampToGround"
            },
            "gx:coord": "-79.38061499999999 43.652823 0"
          },
          "TimeSpan": {
            "begin": "2017-12-17T21:49:17.607Z",
            "end": "2017-12-17T22:58:04.389Z"
          }
        },
        {
          "name": "Walking",
          "address": "",
          "ExtendedData": {
            "Data": [
              {
                "@name": "Email",
                "value": "melikesolenakin@gmail.com"
              },
              {
                "@name": "Category",
                "value": "Walking"
              },
              {
                "@name": "Distance",
                "value": "234"
              }
            ]
          },
          "description": " Walking from 2017-12-17T22:58:04.389Z to 2017-12-17T22:59:35.389Z. Distance 234m ",
          "Point": {
            "coordinates": ""
          },
          "gx:Track": {
            "altitudeMode": {
              "@xmlns": "http://www.opengis.net/kml/2.2",
              "#text": "clampToGround"
            },
            "gx:coord": [
              "-79.38061499999999 43.652823 0",
              "-79.38061499999999 43.652823 0",
              "-79.3799368 43.6542713 0",
              "-79.3797474349258 43.65371125810014 0",
              "-79.3797474349258 43.65371125810014 0"
            ]
          },
          "TimeSpan": {
            "begin": "2017-12-17T22:58:04.389Z",
            "end": "2017-12-17T22:59:35.389Z"
          }
        },
        {
          "name": "Downtown Yonge",
          "address": "Toronto, ON",
          "ExtendedData": {
            "Data": [
              {
                "@name": "Email",
                "value": "melikesolenakin@gmail.com"
              },
              {
                "@name": "Category",
                "value": ""
              },
              {
                "@name": "Distance",
                "value": "0"
              }
            ]
          },
          "description": "  from 2017-12-17T22:59:35.389Z to 2017-12-17T23:37:04.997Z. Distance 0m ",
          "Point": {
            "coordinates": ""
          },
          "gx:Track": {
            "altitudeMode": {
              "@xmlns": "http://www.opengis.net/kml/2.2",
              "#text": "clampToGround"
            },
            "gx:coord": "-79.3817523 43.6574254 0"
          },
          "TimeSpan": {
            "begin": "2017-12-17T22:59:35.389Z",
            "end": "2017-12-17T23:37:04.997Z"
          }
        },
        {
          "name": "Walking",
          "address": "",
          "ExtendedData": {
            "Data": [
              {
                "@name": "Email",
                "value": "melikesolenakin@gmail.com"
              },
              {
                "@name": "Category",
                "value": "Walking"
              },
              {
                "@name": "Distance",
                "value": "1831"
              }
            ]
          },
          "description": " Walking from 2017-12-17T23:37:04.997Z to 2017-12-18T00:01:02.895Z. Distance 1831m ",
          "Point": {
            "coordinates": ""
          },
          "gx:Track": {
            "altitudeMode": {
              "@xmlns": "http://www.opengis.net/kml/2.2",
              "#text": "clampToGround"
            },
            "gx:coord": [
              "-79.3797474349258 43.65371125810014 0",
              "-79.3797474349258 43.65371125810014 0",
              "-79.3800266 43.654381 0",
              "-79.3806589 43.6553334 0",
              "-79.3806259 43.6559969 0",
              "-79.3822557 43.6560117 0",
              "-79.3850275 43.65544 0",
              "-79.3875471 43.6543552 0",
              "-79.3985805 43.6541636 0",
              "-79.3988184 43.6543246 0",
              "-79.39847058898654 43.65395639581243 0",
              "-79.39847058898654 43.65395639581243 0"
            ]
          },
          "TimeSpan": {
            "begin": "2017-12-17T23:37:04.997Z",
            "end": "2017-12-18T00:01:02.895Z"
          }
        },
        {
          "name": "Grange Park",
          "address": "Toronto, ON",
          "ExtendedData": {
            "Data": [
              {
                "@name": "Email",
                "value": "melikesolenakin@gmail.com"
              },
              {
                "@name": "Category",
                "value": ""
              },
              {
                "@name": "Distance",
                "value": "0"
              }
            ]
          },
          "description": "  from 2017-12-18T00:01:02.895Z to 2017-12-18T00:57:10.066Z. Distance 0m ",
          "Point": {
            "coordinates": ""
          },
          "gx:Track": {
            "altitudeMode": {
              "@xmlns": "http://www.opengis.net/kml/2.2",
              "#text": "clampToGround"
            },
            "gx:coord": "-79.3930124 43.6537341 0"
          },
          "TimeSpan": {
            "begin": "2017-12-18T00:01:02.895Z",
            "end": "2017-12-18T00:57:10.066Z"
          }
        },
        {
          "name": "Driving",
          "address": "",
          "ExtendedData": {
            "Data": [
              {
                "@name": "Email",
                "value": "melikesolenakin@gmail.com"
              },
              {
                "@name": "Category",
                "value": "Driving"
              },
              {
                "@name": "Distance",
                "value": "4263"
              }
            ]
          },
          "description": " Driving from 2017-12-18T00:57:10.066Z to 2017-12-18T01:10:21.138Z. Distance 4263m ",
          "Point": {
            "coordinates": ""
          },
          "gx:Track": {
            "altitudeMode": {
              "@xmlns": "http://www.opengis.net/kml/2.2",
              "#text": "clampToGround"
            },
            "gx:coord": [
              "-79.39847058898654 43.65395639581243 0",
              "-79.39847058898654 43.65395639581243 0",
              "-79.3996924 43.6550107 0",
              "-79.4004389 43.6578339 0",
              "-79.3909908 43.6599301 0",
              "-79.3940782 43.6684539 0",
              "-79.3979654 43.6781652 0",
              "-79.3917206 43.6845125 0",
              "-79.3916563 43.6847358 0",
              "-79.3916563 43.6847358 0"
            ]
          },
          "TimeSpan": {
            "begin": "2017-12-18T00:57:10.066Z",
            "end": "2017-12-18T01:10:21.138Z"
          }
        },
        {
          "name": "Home",
          "address": "7 Jackes Ave, Toronto, ON M4T 1E3",
          "ExtendedData": {
            "Data": [
              {
                "@name": "Email",
                "value": "melikesolenakin@gmail.com"
              },
              {
                "@name": "Category",
                "value": ""
              },
              {
                "@name": "Distance",
                "value": "0"
              }
            ]
          },
          "description": "  from 2017-12-18T01:10:21.138Z to 2017-12-18T14:08:11.348Z. Distance 0m ",
          "Point": {
            "coordinates": ""
          },
          "gx:Track": {
            "altitudeMode": {
              "@xmlns": "http://www.opengis.net/kml/2.2",
              "#text": "clampToGround"
            },
            "gx:coord": "-79.3916563 43.6847358 0"
          },
          "TimeSpan": {
            "begin": "2017-12-18T01:10:21.138Z",
            "end": "2017-12-18T14:08:11.348Z"
          }
        }
      ]
    }
  }
}